Metadata-Version: 2.1
Name: a-pandas-ex-memorydump-to-df
Version: 0.11
Summary: Load a ProcDump memory dump into a Pandas DataFrame
Home-page: https://github.com/hansalemaos/a_pandas_ex_memorydump_to_df
Author: Johannes Fischer
Author-email: <aulasparticularesdealemaosp@gmail.com>
License: MIT
Keywords: hacking,debug,debugging
Classifier: Development Status :: 4 - Beta
Classifier: Programming Language :: Python :: 3 :: Only
Classifier: Programming Language :: Python :: 3.9
Classifier: Topic :: Scientific/Engineering :: Visualization
Classifier: Topic :: Software Development :: Libraries :: Python Modules
Classifier: Topic :: Text Editors :: Text Processing
Classifier: Topic :: Text Processing :: General
Classifier: Topic :: Text Processing :: Indexing
Classifier: Topic :: Text Processing :: Filters
Classifier: Topic :: Utilities
License-File: LICENSE.rst
Requires-Dist: flatten-everything
Requires-Dist: numpy
Requires-Dist: pandas
Requires-Dist: pykd
Requires-Dist: PyPDump
Requires-Dist: touchtouch
Requires-Dist: winappdbg
